{
  "id": 1402,
  "type": "kanji",
  "level": 29,
  "characters": {
    "type": "text",
    "value": "緊"
  },
  "primaryReading": "きん",
  "readings": [
    {
      "primary": true,
      "reading": "きん",
      "type": "onyomi"
    }
  ],
  "primaryMeaning": "Tense",
  "otherMeanings": [],
  "meaningMnemonic": "The <radical>servant</radical> sits on a <radical>stool</radical>, holding a piece of <radical>thread</radical>, looking very <kanji>tense</kanji>. ",
  "readingMnemonic": "You ask the servant why they're so <kanji>tense</kanji>, and they say they've been assigned to assassinate the <reading>Kin</reading>g (きん) of England with this piece of thread.",
  "wkSlug": "緊",
  "related": {
    "radicals": [
      323,
      30,
      86
    ],
    "vocabularies": [
      5231,
      5271,
      5407
    ]
  }
}