{
  "id": 1521,
  "type": "kanji",
  "level": 33,
  "characters": {
    "type": "text",
    "value": "宣"
  },
  "primaryReading": "せん",
  "readings": [
    {
      "primary": true,
      "reading": "せん",
      "type": "onyomi"
    },
    {
      "primary": false,
      "reading": "のたま",
      "type": "kunyomi"
    }
  ],
  "primaryMeaning": "Proclaim",
  "otherMeanings": [],
  "meaningMnemonic": "Someone climbs onto the <radical>roof</radical> from the <radical>ground</radical> when <radical>dawn</radical> comes to <kanji>proclaim</kanji> that a new day has begun! They proclaim this at the top of their lungs!",
  "readingMnemonic": "The thing that climbs up on the roof to <kanji>proclaim</kanji> that the new day is here is a <reading>cen</reading>taur (せん). Ohoho, did you think I was going to say it was a rooster? Wrong! Centaurs are taller than humans and roosters, so when they climb onto the roof with their horse legs they can see dawn starting before anyone else.",
  "wkSlug": "宣",
  "related": {
    "radicals": [
      78,
      1,
      293
    ],
    "vocabularies": [
      5634,
      5635,
      5840
    ]
  }
}