{
  "id": 1524,
  "type": "kanji",
  "level": 33,
  "characters": {
    "type": "text",
    "value": "拡"
  },
  "primaryReading": "かく",
  "readings": [
    {
      "primary": true,
      "reading": "かく",
      "type": "onyomi"
    },
    {
      "primary": false,
      "reading": "ひろ",
      "type": "kunyomi"
    }
  ],
  "primaryMeaning": "Extend",
  "otherMeanings": [],
  "meaningMnemonic": "To make your <radical>fingers</radical> <radical>wide</radical> you <kanji>extend</kanji> them.",
  "readingMnemonic": "As you <kanji>extend</kanji> your fingers a <reading>cock</reading> (かく) comes running by and runs straight into them. Bu-COCK!",
  "wkSlug": "拡",
  "related": {
    "radicals": [
      63,
      382
    ],
    "vocabularies": [
      5640,
      5641,
      5642
    ]
  }
}