{
  "id": 1687,
  "type": "kanji",
  "level": 38,
  "characters": {
    "type": "text",
    "value": "傾"
  },
  "primaryReading": "けい",
  "readings": [
    {
      "primary": true,
      "reading": "けい",
      "type": "onyomi"
    },
    {
      "primary": false,
      "reading": "かたむ",
      "type": "kunyomi"
    }
  ],
  "primaryMeaning": "Lean",
  "otherMeanings": [],
  "meaningMnemonic": "You <radical>change</radical> this <radical>geoduck</radical> because you want it to <kanji>lean</kanji>. Right now it's standing up straight, but you want it to lean to one side instead. ",
  "readingMnemonic": "To get the geoduck to <kanji>lean</kanji> you put a piece of <reading>ca</reading>ke (けい) on one of its sides.",
  "wkSlug": "傾",
  "related": {
    "radicals": [
      311,
      184
    ],
    "vocabularies": [
      6182,
      6183,
      6342
    ]
  }
}