{
  "id": 1714,
  "type": "kanji",
  "level": 39,
  "characters": {
    "type": "text",
    "value": "控"
  },
  "primaryReading": "ひか",
  "readings": [
    {
      "primary": true,
      "reading": "ひか",
      "type": "kunyomi"
    },
    {
      "primary": false,
      "reading": "こう",
      "type": "onyomi"
    }
  ],
  "primaryMeaning": "Abstain",
  "otherMeanings": [],
  "meaningMnemonic": "Raise your <radical>fingers</radical> to the <radical>sky</radical> to symbolize that you <kanji>abstain</kanji> from something. If someone offers you fur coats, raise your fingers to abstain. If someone tries to get you to bully someone, raise your fingers to abstain.",
  "readingMnemonic": "This symbol to <kanji>abstain</kanji> comes from the <reading>hica</reading>tee (ひか) turtle. The hicatee is a Central American river turtle hunted for its meat, eggs, and shell. Therefore, the poor hicatee are endangered. So people started to rally around them, abstaining from hurting them anymore. They raised their fingers to the sky and shouted, \"I abstain from harming these hicatee!\"",
  "wkSlug": "控",
  "related": {
    "radicals": [
      63,
      370
    ],
    "vocabularies": [
      6454,
      8690
    ]
  }
}