{
  "id": 2126,
  "type": "kanji",
  "level": 51,
  "characters": {
    "type": "text",
    "value": "濯"
  },
  "primaryReading": "たく",
  "readings": [
    {
      "primary": true,
      "reading": "たく",
      "type": "onyomi"
    },
    {
      "primary": false,
      "reading": "すす",
      "type": "kunyomi"
    },
    {
      "primary": false,
      "reading": "ゆす",
      "type": "kunyomi"
    },
    {
      "primary": false,
      "reading": "そそぐ",
      "type": "kunyomi"
    }
  ],
  "primaryMeaning": "Wash",
  "otherMeanings": [],
  "meaningMnemonic": "A <radical>tsunami</radical> is coming so you take your two <radical>wolverines</radical> and your <radical>turkey</radical> out for a <kanji>wash</kanji>. It's the only way you can get them clean at once without the wolverines fighting over the turkey and somebody getting hurt. The tsunami is big enough to wash them all before anything bad happens.",
  "readingMnemonic": "Once they're nice and <kanji>wash</kanji>ed you need to subdue them by poking each of them with a <reading>tack</reading> (たく). The tack has special sleeping medicine on it, so once they're nice and clean you can put them back in their cages without them trying to eat each other.",
  "wkSlug": "濯",
  "related": {
    "radicals": [
      103,
      105,
      240
    ],
    "vocabularies": [
      7806,
      7807,
      7808,
      8813
    ]
  }
}