{
  "id": 2978,
  "type": "vocabulary",
  "level": 7,
  "characters": {
    "type": "text",
    "value": "先週"
  },
  "primaryMeaning": "Last Week",
  "meaningMnemonic": "The <kanji>previous</kanji> <kanji>week</kanji> was <vocabulary>last week</vocabulary>.",
  "primaryReading": "せんしゅう",
  "readingMnemonic": "This is a jukugo word, which usually means on'yomi readings from the kanji. If you know the readings of your kanji you'll know how to read this as well.",
  "otherMeanings": [],
  "otherReadings": [],
  "wkSlug": "先週",
  "related": {
    "radicals": [
      5,
      17,
      28,
      114,
      169
    ],
    "kanjis": [
      543,
      672
    ]
  },
  "readingAudio": [
    {
      "reading": "せんしゅう",
      "url": "https://files.wanikani.com/c7hia5odvk35tkju7dg19obf3czl"
    }
  ]
}