{
  "id": 3673,
  "type": "vocabulary",
  "level": 14,
  "characters": {
    "type": "text",
    "value": "完全"
  },
  "primaryMeaning": "Complete",
  "meaningMnemonic": "When something is <kanji>all</kanji> <kanji>perfect</kanji> it is <vocabulary>complete</vocabulary>. Not only that, but it's <vocabulary>perfect</vocabulary> (because it's ALL perfect, not just partially so).",
  "primaryReading": "かんぜん",
  "readingMnemonic": "This is a jukugo word, which usually means on'yomi readings from the kanji. If you know the readings of your kanji you'll know how to read this as well.",
  "otherMeanings": [
    "Perfect",
    "Perfection",
    "Completeness"
  ],
  "otherReadings": [],
  "wkSlug": "完全",
  "related": {
    "radicals": [
      78,
      64,
      8764,
      48
    ],
    "kanjis": [
      904,
      610
    ]
  },
  "readingAudio": [
    {
      "reading": "かんぜん",
      "url": "https://files.wanikani.com/jmql71bwjo9wwyxqwveskqdy8v3a"
    }
  ]
}