{
  "id": 391,
  "type": "radical",
  "level": 30,
  "characters": {
    "type": "text",
    "value": "冘"
  },
  "primaryMeaning": "Pirate",
  "otherMeanings": [],
  "meaningMnemonic": "This kind of looks like big (大), which I think you'll remember you learned by pretending this was a big guy. This big guy, however, has a funny leg... a peg leg. That makes him a <radical>pirate</radical>. Also, his arms are in the \"YARRRR\" position.",
  "wkSlug": "pirate",
  "related": {
    "kanjis": [
      1432,
      1865
    ],
    "vocabularies": [
      5329,
      6731,
      6732,
      6733,
      7045,
      7898
    ]
  }
}