{
  "id": 3989,
  "type": "vocabulary",
  "level": 17,
  "characters": {
    "type": "text",
    "value": "幻覚"
  },
  "primaryMeaning": "Hallucination",
  "meaningMnemonic": "An <kanji>illusion</kanji> you have when you're <kanji>awake</kanji> is a <vocabulary>hallucination</vocabulary>. ",
  "primaryReading": "げんかく",
  "readingMnemonic": "This is a jukugo word, which usually means on'yomi readings from the kanji. If you know the readings of your kanji you'll know how to read this as well.",
  "otherMeanings": [],
  "otherReadings": [],
  "wkSlug": "幻覚",
  "related": {
    "radicals": [
      87,
      8780,
      8769,
      91
    ],
    "kanjis": [
      1027,
      1025
    ]
  },
  "readingAudio": [
    {
      "reading": "げんかく",
      "url": "https://files.wanikani.com/1gopxpmu0s9enkjumc22j2n7zrbl"
    }
  ]
}