{
  "id": 511,
  "type": "kanji",
  "level": 3,
  "characters": {
    "type": "text",
    "value": "牛"
  },
  "primaryReading": "ぎゅう",
  "readings": [
    {
      "primary": true,
      "reading": "ぎゅう",
      "type": "onyomi"
    },
    {
      "primary": false,
      "reading": "うし",
      "type": "kunyomi"
    }
  ],
  "primaryMeaning": "Cow",
  "otherMeanings": [],
  "meaningMnemonic": "The radical and the kanji for <kanji>cow</kanji> are exactly the same! That makes it easy to remember, so long as you know your radicals well enough.",
  "readingMnemonic": "Have you ever heard of わ<reading>ぎゅう</reading> (wagyu) beef? That ぎゅう is this ぎゅう.",
  "wkSlug": "牛",
  "related": {
    "radicals": [
      126
    ],
    "vocabularies": [
      2619,
      2768,
      3403,
      4646,
      5754
    ]
  }
}