{
  "id": 5782,
  "type": "vocabulary",
  "level": 34,
  "characters": {
    "type": "text",
    "value": "注射"
  },
  "primaryMeaning": "Shot",
  "meaningMnemonic": "When you <kanji>shoot</kanji> something into someone that you actually have to <kanji>pour</kanji> (aka a liquid), you're shooting them up with a needle, giving them a <vocabulary>shot</vocabulary> / <vocabulary>injection</vocabulary>.",
  "primaryReading": "ちゅうしゃ",
  "readingMnemonic": "This is a jukugo word that uses the on'yomi readings of the kanji. You should be able to read this on your own.",
  "otherMeanings": [
    "Injection"
  ],
  "otherReadings": [],
  "wkSlug": "注射",
  "related": {
    "radicals": [
      103,
      154,
      234,
      74
    ],
    "kanjis": [
      794,
      1561
    ]
  },
  "readingAudio": [
    {
      "reading": "ちゅうしゃ",
      "url": "https://files.wanikani.com/f5xu3mrk75bhbgolmicnm8hmtjfg"
    }
  ]
}