{
  "id": 6360,
  "type": "vocabulary",
  "level": 40,
  "characters": {
    "type": "text",
    "value": "顧みる"
  },
  "primaryMeaning": "To Look Back On Something",
  "meaningMnemonic": "Because the hiragana ends with an う sound, you know this word is a verb. The kanji itself means <kanji>review</kanji>. What do you do when you review something? You look back on it. Meaning <vocabulary>to look back on something</vocabulary> or <vocabulary>to reflect on something</vocabulary>. This can also mean <vocabulary>to be attentive to someone</vocabulary>, for example your family.\n\nThis is a transitive verb, meaning it takes a direct object. You look back on the past, you reflect on the consequences of your actions, and you're attentive to your family.",
  "primaryReading": "かえりみる",
  "readingMnemonic": "For the reading, think about another word that is similar: 帰る. With 帰る you are returning to somewhere. With this word, you're returning to look back on something. They share the same first part reading, so you should take advantage of that. 帰る → かえり.",
  "otherMeanings": [
    "To Reflect On Something",
    "To Be Attentive To Someone"
  ],
  "otherReadings": [],
  "wkSlug": "顧みる",
  "related": {
    "radicals": [
      378,
      184
    ],
    "kanjis": [
      1742
    ]
  },
  "readingAudio": [
    {
      "reading": "かえりみる",
      "url": "https://files.wanikani.com/rn8ezm3f1glmrqpj4m37ponqna7j"
    }
  ]
}