{
  "id": 6861,
  "type": "vocabulary",
  "level": 45,
  "characters": {
    "type": "text",
    "value": "肌色"
  },
  "primaryMeaning": "Skin Color",
  "meaningMnemonic": "<kanji>Skin</kanji> <kanji>color</kanji> is <vocabulary>skin color</vocabulary>, or <vocabulary>skin tone</vocabulary>.\n\nThis word originally referred to a pale orange or peach color, and sometimes you'll still see it used that way. But labeling that as 肌色 wasn't inclusive of all skin tones. Now, it simply refers to skin color in general.",
  "primaryReading": "はだいろ",
  "readingMnemonic": "The readings are the vocab kun'yomi readings of each kanji, 肌 and 色 combined into one.",
  "otherMeanings": [
    "Skin Tone"
  ],
  "otherReadings": [],
  "wkSlug": "肌色",
  "related": {
    "radicals": [
      43,
      177,
      110
    ],
    "kanjis": [
      1908,
      579
    ]
  },
  "readingAudio": [
    {
      "reading": "はだいろ",
      "url": "https://files.wanikani.com/d3dr8xkftedmlkxpdck38mdkbpfo"
    }
  ]
}