{
  "id": 8421,
  "type": "vocabulary",
  "level": 57,
  "characters": {
    "type": "text",
    "value": "発酵"
  },
  "primaryMeaning": "Fermentation",
  "meaningMnemonic": "When you <kanji>ferment</kanji> something it makes a <kanji>departure</kanji> from what it originally was and transforms during <vocabulary>fermentation</vocabulary> into something new.",
  "primaryReading": "はっこう",
  "readingMnemonic": "This is a jukugo word that uses the on'yomi readings of the kanji. You should be able to read this on your own.",
  "otherMeanings": [],
  "otherReadings": [],
  "wkSlug": "発酵",
  "related": {
    "radicals": [
      168,
      171,
      182,
      418
    ],
    "kanjis": [
      729,
      2354
    ]
  },
  "readingAudio": [
    {
      "reading": "はっこう",
      "url": "https://files.wanikani.com/y0f9ns5q7am0ow6p3adoxc0mxaek"
    }
  ]
}