{
  "id": 1290,
  "type": "kanji",
  "character": "貯",
  "primaryMeaning": "Savings",
  "otherMeanings": [],
  "primaryReading": "ちょ",
  "readings": [
    {
      "reading": "ちょ",
      "primary": true,
      "type": "onyomi"
    },
    {
      "reading": "たくわ",
      "primary": false,
      "type": "kunyomi"
    }
  ],
  "readingMnemonic": "When you want to withdraw from your <kanji>savings</kanji> you force yourself to use <reading>cho</reading>psticks (ちょ) to pick up the shellfish. They're especially slippery, hard to use chopsticks too, that way it's really hard to take too much out of your savings.",
  "meaningMnemonic": "You keep all of your <radical>shellfish</radical> under a <radical>roof</radical> down the <radical>street</radical> and it's your <kanji>savings</kanji>. Shellfish used to be used as money way back, and these aren't shellfish you're spending, they're ones you're saving up for later.",
  "vocabularyIds": [
    4974,
    4975,
    5195,
    7162
  ],
  "radicalIds": [
    94,
    78,
    27
  ],
  "wanikaniUrl": "https://www.wanikani.com/kanji/%E8%B2%AF"
}