{
  "id": 1413,
  "type": "kanji",
  "character": "魅",
  "primaryMeaning": "Alluring",
  "otherMeanings": [],
  "primaryReading": "み",
  "readings": [
    {
      "reading": "み",
      "primary": true,
      "type": "onyomi"
    }
  ],
  "readingMnemonic": "This <kanji>alluring</kanji> demon on a jet wants one thing and one thing only. <reading>Me</reading>at (み). Human meat. This demon needs human meat to survive so he is taking his jet into the city to feast on some meat.",
  "meaningMnemonic": "A <radical>demon</radical> on a <radical>jet</radical> is pretty <kanji>alluring</kanji>. Demons themselves are pretty intriguing, but put one on a jet? Now that’s alluring.",
  "vocabularyIds": [
    5296
  ],
  "radicalIds": [
    292,
    134
  ],
  "wanikaniUrl": "https://www.wanikani.com/kanji/%E9%AD%85"
}