{
  "id": 2356,
  "type": "kanji",
  "character": "遮",
  "primaryMeaning": "Intercept",
  "otherMeanings": [],
  "primaryReading": "しゃ",
  "readings": [
    {
      "reading": "しゃ",
      "primary": true,
      "type": "onyomi"
    },
    {
      "reading": "さえぎ",
      "primary": false,
      "type": "kunyomi"
    }
  ],
  "readingMnemonic": "You manage to <kanji>intercept</kanji> the <reading>sha</reading>man (しゃ) who was just about to open the door to your yurt, and instead you crash right into him.",
  "meaningMnemonic": "You're riding your <radical>scooter</radical> toward your <radical>yurt</radical> as fast as you can because someone is trying to get in there to <radical>boil</radical> your water and you want to <kanji>intercept</kanji> them.",
  "vocabularyIds": [
    8417,
    8418,
    8584
  ],
  "radicalIds": [
    114,
    8787,
    131
  ],
  "wanikaniUrl": "https://www.wanikani.com/kanji/%E9%81%AE"
}