{
  "id": 2589,
  "type": "vocabulary",
  "characters": "二万",
  "primaryMeaning": "Twenty Thousand",
  "otherMeanings": [],
  "primaryReading": "にまん",
  "otherReadings": [],
  "kanji": [
    {
      "id": 441,
      "character": "二",
      "readings": [
        "に",
        "ふた"
      ]
    },
    {
      "id": 495,
      "character": "万",
      "readings": [
        "まん",
        "ばん"
      ]
    }
  ],
  "meaningMnemonic": "When you have <kanji>two</kanji> <kanji>ten thousand</kanji>s, you have <vocabulary>twenty thousand</vocabulary>.",
  "readingMnemonic": "This is a jukugo word, which usually means on'yomi readings from the kanji. If you know the readings of your kanji you'll know how to read this as well.",
  "wanikaniUrl": "https://www.wanikani.com/vocabulary/%E4%BA%8C%E4%B8%87",
  "elements": [
    {
      "type": "kanji",
      "value": "二",
      "id": 441,
      "reading": "に"
    },
    {
      "type": "kanji",
      "value": "万",
      "id": 495,
      "reading": "まん"
    }
  ]
}