{
  "id": 6270,
  "type": "vocabulary",
  "characters": "壁",
  "primaryMeaning": "Wall",
  "otherMeanings": [],
  "primaryReading": "かべ",
  "otherReadings": [],
  "kanji": [
    {
      "id": 1715,
      "character": "壁",
      "readings": [
        "かべ",
        "へき"
      ]
    }
  ],
  "meaningMnemonic": "The kanji and the word are exactly the same. That means they share meanings as well.",
  "readingMnemonic": "The reading is the one you learned with the kanji!",
  "wanikaniUrl": "https://www.wanikani.com/vocabulary/%E5%A3%81",
  "elements": [
    {
      "type": "kanji",
      "value": "壁",
      "id": 1715,
      "reading": "かべ"
    }
  ]
}