{
  "id": 7499,
  "type": "vocabulary",
  "characters": "編集者",
  "primaryMeaning": "Editor",
  "otherMeanings": [],
  "primaryReading": "へんしゅうしゃ",
  "otherReadings": [],
  "kanji": [
    {
      "id": 1445,
      "character": "編",
      "readings": [
        "へん",
        "あ"
      ]
    },
    {
      "id": 754,
      "character": "集",
      "readings": [
        "しゅう",
        "あつ"
      ]
    },
    {
      "id": 690,
      "character": "者",
      "readings": [
        "しゃ",
        "もの"
      ]
    }
  ],
  "meaningMnemonic": "An <kanji>edit</kanji> is 編集. <kanji>Someone</kanji> who does those edits is an <vocabulary>editor</vocabulary>!",
  "readingMnemonic": "This is a jukugo word that uses the on'yomi readings of the kanji. You should be able to read this on your own. Also, the readings from 編集 should help you.",
  "wanikaniUrl": "https://www.wanikani.com/vocabulary/%E7%B7%A8%E9%9B%86%E8%80%85",
  "elements": [
    {
      "type": "kanji",
      "value": "編",
      "id": 1445,
      "reading": "へん"
    },
    {
      "type": "kanji",
      "value": "集",
      "id": 754,
      "reading": "しゅう"
    },
    {
      "type": "kanji",
      "value": "者",
      "id": 690,
      "reading": "しゃ"
    }
  ]
}