{
  "id": 7711,
  "type": "vocabulary",
  "characters": "指差す",
  "primaryMeaning": "To Point At",
  "otherMeanings": [
    "To Point To"
  ],
  "primaryReading": "ゆびさす",
  "otherReadings": [],
  "kanji": [
    {
      "id": 797,
      "character": "指",
      "readings": [
        "し",
        "ゆび",
        "さ"
      ]
    },
    {
      "id": 1235,
      "character": "差",
      "readings": [
        "さ",
        "さ"
      ]
    }
  ],
  "meaningMnemonic": "When you want to use your <kanji>finger</kanji> to explain the <kanji>distinction</kanji> between more than one thing, you need <vocabulary>to point at</vocabulary> it. Otherwise the person you're talking to won't be able to tell which one you're talking about.\n\nIn general, 指差す specifically means using one’s index finger to physically point at something or someone.",
  "readingMnemonic": "The readings for this word are both kun'yomi readings. You've learned both of these readings by now so you should be able to read this on your own.",
  "wanikaniUrl": "https://www.wanikani.com/vocabulary/%E6%8C%87%E5%B7%AE%E3%81%99",
  "elements": [
    {
      "type": "kanji",
      "value": "指",
      "id": 797,
      "reading": "ゆび"
    },
    {
      "type": "kanji",
      "value": "差",
      "id": 1235,
      "reading": "さ"
    },
    {
      "type": "kana",
      "value": "す"
    }
  ]
}