{
  "id": 8437,
  "type": "vocabulary",
  "characters": "凌ぐ",
  "primaryMeaning": "To Endure",
  "otherMeanings": [
    "To Keep Out",
    "To Stave Off",
    "To Surpass",
    "To Outrank",
    "To Eclipse"
  ],
  "primaryReading": "しのぐ",
  "otherReadings": [],
  "kanji": [
    {
      "id": 2395,
      "character": "凌",
      "readings": [
        "しの",
        "りょう"
      ]
    }
  ],
  "meaningMnemonic": "This word consists of kanji with hiragana attached. Because the hiragana ends with an う sound, you know this word is a verb. The kanji itself means <kanji>endure</kanji>, so the verb version is <vocabulary>to endure</vocabulary> or <vocabulary>to keep out</vocabulary>.",
  "readingMnemonic": "Since this word consists of a kanji with hiragana attached, you can bet that it will use the kun'yomi reading. You learned this reading already so you should be able to read it!",
  "wanikaniUrl": "https://www.wanikani.com/vocabulary/%E5%87%8C%E3%81%90",
  "elements": [
    {
      "type": "kanji",
      "value": "凌",
      "id": 2395,
      "reading": "しの"
    },
    {
      "type": "kana",
      "value": "ぐ"
    }
  ]
}