{
  "id": 1565,
  "type": "kanji",
  "character": "推",
  "primaryMeaning": "Infer",
  "otherMeanings": [],
  "primaryReading": "すい",
  "readings": [
    {
      "reading": "すい",
      "primary": true,
      "type": "onyomi"
    },
    {
      "reading": "お",
      "primary": false,
      "type": "kunyomi"
    }
  ],
  "readingMnemonic": "You were able to <kanji>infer</kanji> the turkey's plan, so now it's your turn. You look around and see the only way out... is to <reading>swi</reading>ng (すい) to safety! How did I infer that, dear Watson? Why, isn't it obvious! There are vines here. Turkeys can't fly. So I shall swing my way to freedom!",
  "meaningMnemonic": "If a <radical>turkey</radical> is pointing its <radical>fingers</radical> at you, you can <kanji>infer</kanji> that it wants revenge. This turkey knows you killed his brother for dinner last night, and now he’s going to make you pay. You infer that this turkey is going to take their fingers and wrap them around your neck.",
  "vocabularyIds": [
    5791,
    5792,
    5793,
    5864,
    7344
  ],
  "radicalIds": [
    63,
    240
  ],
  "wanikaniUrl": "https://www.wanikani.com/kanji/%E6%8E%A8"
}