{
  "id": 3170,
  "type": "vocabulary",
  "characters": "最終",
  "primaryMeaning": "Last",
  "otherMeanings": [
    "Final",
    "The Last",
    "The Final"
  ],
  "primaryReading": "さいしゅう",
  "otherReadings": [],
  "kanji": [
    {
      "id": 774,
      "character": "最",
      "readings": [
        "さい",
        "もっと"
      ]
    },
    {
      "id": 745,
      "character": "終",
      "readings": [
        "しゅう",
        "おわ",
        "お"
      ]
    }
  ],
  "meaningMnemonic": "The <kanji>most</kanji> <kanji>end</kanji> thing is the <vocabulary>last</vocabulary> thing. It is mainly used to refer to the <vocabulary>last</vocabulary> of an ordered sequence.",
  "readingMnemonic": "This is a jukugo word, which usually means on'yomi readings from the kanji. If you know the readings of your kanji you'll know how to read this as well.",
  "wanikaniUrl": "https://www.wanikani.com/vocabulary/%E6%9C%80%E7%B5%82",
  "elements": [
    {
      "type": "kanji",
      "value": "最",
      "id": 774,
      "reading": "さい"
    },
    {
      "type": "kanji",
      "value": "終",
      "id": 745,
      "reading": "しゅう"
    }
  ]
}