{
  "id": 3193,
  "type": "vocabulary",
  "level": 10,
  "characters": {
    "type": "text",
    "value": "工業"
  },
  "primaryMeaning": "Industry",
  "meaningMnemonic": "The <kanji>business</kanji> of <kanji>industry</kanji> is... well... <vocabulary>industry</vocabulary>.",
  "primaryReading": "こうぎょう",
  "readingMnemonic": "This is a jukugo word, which usually means on'yomi readings from the kanji. If you know the readings of your kanji you'll know how to read this as well.",
  "otherMeanings": [],
  "otherReadings": [],
  "urls": {
    "wanikani": "https://www.wanikani.com/vocabulary/%E5%B7%A5%E6%A5%AD",
    "graph": "/v/vocabulary/3193"
  },
  "related": {
    "radicals": [
      25,
      8768,
      136,
      2
    ],
    "kanjis": [
      457,
      756
    ]
  }
}