{
  "id": 4285,
  "type": "vocabulary",
  "characters": "機嫌",
  "primaryMeaning": "Mood",
  "otherMeanings": [
    "Temper"
  ],
  "primaryReading": "きげん",
  "otherReadings": [],
  "kanji": [
    {
      "id": 1090,
      "character": "機",
      "readings": [
        "き",
        "はた"
      ]
    },
    {
      "id": 1104,
      "character": "嫌",
      "readings": [
        "けん",
        "げん",
        "いや",
        "きら"
      ]
    }
  ],
  "meaningMnemonic": "<kanji>Machine</kanji>s <kanji>dislike</kanji> everything. Their <vocabulary>mood</vocabulary>, or <vocabulary>temper</vocabulary>, is very sour. What about your mood?",
  "readingMnemonic": "This is a jukugo word, which usually means on'yomi readings from the kanji. If you know the readings of your kanji you'll know how to read this as well. けん gets changed to げん, though, so don't let that ruin your <vocabulary>mood</vocabulary>.",
  "wanikaniUrl": "https://www.wanikani.com/vocabulary/%E6%A9%9F%E5%AB%8C",
  "elements": [
    {
      "type": "kanji",
      "value": "機",
      "id": 1090,
      "reading": "き"
    },
    {
      "type": "kanji",
      "value": "嫌",
      "id": 1104,
      "reading": "げん"
    }
  ]
}