{
  "id": 4737,
  "type": "vocabulary",
  "characters": "質問",
  "primaryMeaning": "Question",
  "otherMeanings": [],
  "primaryReading": "しつもん",
  "otherReadings": [],
  "kanji": [
    {
      "id": 1242,
      "character": "質",
      "readings": [
        "しつ",
        "しち"
      ]
    },
    {
      "id": 859,
      "character": "問",
      "readings": [
        "もん",
        "と",
        "とん"
      ]
    }
  ],
  "meaningMnemonic": "A <kanji>quality</kanji> <kanji>problem</kanji> is worth a <vocabulary>question</vocabulary>. A low quality problem however... don't ask the question. There are stupid questions, after all.",
  "readingMnemonic": "This is a jukugo word, which usually means on'yomi readings from the kanji. If you know the readings of your kanji you'll know how to read this as well.",
  "wanikaniUrl": "https://www.wanikani.com/vocabulary/%E8%B3%AA%E5%95%8F",
  "elements": [
    {
      "type": "kanji",
      "value": "質",
      "id": 1242,
      "reading": "しつ"
    },
    {
      "type": "kanji",
      "value": "問",
      "id": 859,
      "reading": "もん"
    }
  ]
}