{
  "id": 4977,
  "type": "vocabulary",
  "characters": "輸出する",
  "primaryMeaning": "To Export",
  "otherMeanings": [],
  "primaryReading": "ゆしゅつする",
  "otherReadings": [],
  "kanji": [
    {
      "id": 1221,
      "character": "輸",
      "readings": [
        "ゆ"
      ]
    },
    {
      "id": 483,
      "character": "出",
      "readings": [
        "しゅつ",
        "で",
        "だ"
      ]
    }
  ],
  "meaningMnemonic": "Remember how 輸出 is an export? This is the verb, so this is <vocabulary>to export</vocabulary>.",
  "readingMnemonic": "This is a jukugo word, which usually means on'yomi readings from the kanji. If you know the readings of your kanji you'll know how to read this as well. Will also help to know the word 輸出.",
  "wanikaniUrl": "https://www.wanikani.com/vocabulary/%E8%BC%B8%E5%87%BA%E3%81%99%E3%82%8B",
  "elements": [
    {
      "type": "kanji",
      "value": "輸",
      "id": 1221,
      "reading": "ゆ"
    },
    {
      "type": "kanji",
      "value": "出",
      "id": 483,
      "reading": "しゅつ"
    },
    {
      "type": "kana",
      "value": "する"
    }
  ]
}