{
  "id": 6660,
  "type": "vocabulary",
  "characters": "分裂",
  "primaryMeaning": "Split",
  "otherMeanings": [
    "Division"
  ],
  "primaryReading": "ぶんれつ",
  "otherReadings": [],
  "kanji": [
    {
      "id": 501,
      "character": "分",
      "readings": [
        "ぶん",
        "ふん",
        "ぶ",
        "わ"
      ]
    },
    {
      "id": 1839,
      "character": "裂",
      "readings": [
        "れつ",
        "さ"
      ]
    }
  ],
  "meaningMnemonic": "Things get <kanji>divide</kanji>d and <kanji>split</kanji>. We can just call this a <vocabulary>split</vocabulary> or <vocabulary>division</vocabulary>.\n\n分裂 primarily refers to cells dividing in biology, but it can also figuratively describe an entity or group splitting into separate parts, often due to internal conflict.",
  "readingMnemonic": "This is a jukugo word that uses the on'yomi readings of the kanji. You should be able to read this on your own.",
  "wanikaniUrl": "https://www.wanikani.com/vocabulary/%E5%88%86%E8%A3%82",
  "elements": [
    {
      "type": "kanji",
      "value": "分",
      "id": 501,
      "reading": "ぶん"
    },
    {
      "type": "kanji",
      "value": "裂",
      "id": 1839,
      "reading": "れつ"
    }
  ]
}